LICENSE.txt
MANIFEST.IN
MANIFEST.in
Makefile
README.rst
setup.py
glumpy/__init__.py
glumpy/defaults.py
glumpy/gl.py
glumpy/glm.py
glumpy/log.py
glumpy.egg-info/PKG-INFO
glumpy.egg-info/SOURCES.txt
glumpy.egg-info/dependency_links.txt
glumpy.egg-info/requires.txt
glumpy.egg-info/top_level.txt
glumpy/api/__init__.py
glumpy/api/matplotlib/__init__.py
glumpy/api/matplotlib/axes.py
glumpy/api/matplotlib/figure.py
glumpy/app/__init__.py
glumpy/app/clock.py
glumpy/app/configuration.py
glumpy/app/console.py
glumpy/app/movie.py
glumpy/app/parser.py
glumpy/app/viewport.py
glumpy/app/window/__init__.py
glumpy/app/window/event.py
glumpy/app/window/key.py
glumpy/app/window/mouse.py
glumpy/app/window/window.py
glumpy/app/window/backends/__init__.py
glumpy/app/window/backends/backend_freeglut.py
glumpy/app/window/backends/backend_glfw.py
glumpy/app/window/backends/backend_glfw_deprecated.py
glumpy/app/window/backends/backend_glfw_imgui.py
glumpy/app/window/backends/backend_osxglut.py
glumpy/app/window/backends/backend_pyglet.py
glumpy/app/window/backends/backend_pyside.py
glumpy/app/window/backends/backend_pyside2.py
glumpy/app/window/backends/backend_qt5.py
glumpy/app/window/backends/backend_sdl.py
glumpy/app/window/backends/backend_sdl2.py
glumpy/app/window/backends/backend_template.py
glumpy/data/6x13-bold.npy
glumpy/data/6x13-italic.npy
glumpy/data/6x13-regular.npy
glumpy/data/SourceSansPro-Regular.otf
glumpy/data/__init__.py
glumpy/data/build-spatial-filters.py
glumpy/data/spatial-filters.npy
glumpy/ext/__init__.py
glumpy/ext/ffmpeg_config.py
glumpy/ext/ffmpeg_config_defaults.py
glumpy/ext/ffmpeg_reader.py
glumpy/ext/ffmpeg_tools.py
glumpy/ext/ffmpeg_writer.py
glumpy/ext/glfw.py
glumpy/ext/inputhook.py
glumpy/ext/png.py
glumpy/ext/six.py
glumpy/ext/freetype/__init__.py
glumpy/ext/freetype/ft_errors.py
glumpy/ext/freetype/ft_structs.py
glumpy/ext/freetype/ft_types.py
glumpy/ext/freetype/ft_enums/__init__.py
glumpy/ext/freetype/ft_enums/ft_encodings.py
glumpy/ext/freetype/ft_enums/ft_face_flags.py
glumpy/ext/freetype/ft_enums/ft_fstypes.py
glumpy/ext/freetype/ft_enums/ft_glyph_bbox_modes.py
