Metadata-Version: 2.1
Name: glumpy
Version: 1.2.1
Summary: Fast, scalable & beautiful scientific visualisation
Home-page: http://glumpy.github.io
Download-URL: https://github.com/glumpy/glumpy/releases
Maintainer: Nicolas P. Rougier
Maintainer-email: Nicolas.Rougier@inria.fr
License: BSD License
Keywords: OpenGL,GLSL,2D,3D,Visualisation,Science,Numpy,Graphics,Shaders
Classifier: Development Status :: 5 - Production/Stable
Classifier: Operating System :: MacOS :: MacOS X
Classifier: Operating System :: Microsoft :: Windows
Classifier: Operating System :: POSIX
Classifier: Programming Language :: Python :: 3.8
Classifier: License :: OSI Approved :: BSD License
Classifier: Intended Audience :: Developers
Classifier: Intended Audience :: Science/Research
Classifier: Topic :: Scientific/Engineering :: Visualization
Classifier: Topic :: Multimedia :: Graphics
License-File: LICENSE.txt
Requires-Dist: numpy
Requires-Dist: triangle
Requires-Dist: cython
